chemkin_CS207_G9/__init__.py
chemkin_CS207_G9/auxiliary/__init__.py
chemkin_CS207_G9/auxiliary/check_and_response.py
chemkin_CS207_G9/auxiliary/mathematical_science.py
chemkin_CS207_G9/auxiliary/useful_structure.py
chemkin_CS207_G9/data/__init__.py
chemkin_CS207_G9/data/nasa_thermo.sqlite
chemkin_CS207_G9/data/nasa_thermo_all.sqlite
chemkin_CS207_G9/data/rxns_reversible.xml
chemkin_CS207_G9/math/__init__.py
chemkin_CS207_G9/math/ode_solver.py
chemkin_CS207_G9/parser/Reaction_Creator.py
chemkin_CS207_G9/parser/__init__.py
chemkin_CS207_G9/parser/database_query.py
chemkin_CS207_G9/parser/nasa_thermo.sqlite
chemkin_CS207_G9/parser/xml2dict.py
chemkin_CS207_G9/plotting/NonNetworkPlot.py
chemkin_CS207_G9/plotting/RSGraph.py
chemkin_CS207_G9/plotting/__init__.py
chemkin_CS207_G9/reaction/CoeffLaw.py
chemkin_CS207_G9/reaction/Reaction.py
chemkin_CS207_G9/reaction/ReactionSystem.py
chemkin_CS207_G9/reaction/__init__.py
chemkin_CS207_G9-3.0.dist-info/DESCRIPTION.rst
chemkin_CS207_G9-3.0.dist-info/METADATA
chemkin_CS207_G9-3.0.dist-info/RECORD
chemkin_CS207_G9-3.0.dist-info/WHEEL
chemkin_CS207_G9-3.0.dist-info/metadata.json
chemkin_CS207_G9-3.0.dist-info/top_level.txt
test/__init__.py
test/nasa_thermo.sqlite
test/rxns.xml
test/rxns2.xml
test/rxns_reversible.xml
test/test_CoeffLaw.py
test/test_NonNetworkPlot.py
test/test_RSGraph.py
test/test_Reaction.py
test/test_ReactionSystem.py
test/test_database.sqlite
test/test_database_query.py
test/test_ode_solver.py
test/test_xml2dict.py
