Metadata-Version: 2.0
Name: chemkin-CS207-G9
Version: 3.0
Summary: The vital Chemical Kinetics packages - a life-changing module.
Home-page: https://github.com/cs207group9/cs207-FinalProject/tree/master/chemkin_CS207_G9
Author: Group 9 - CF, YX, JL, BJL
Author-email: blemaire@g.harvard.edu
License: Harvard University
Platform: UNKNOWN
Classifier: Programming Language :: Python :: 3 :: Only
Requires-Python: >=3
